payple_hj3415/__init__.py
payple_hj3415/admin.py
payple_hj3415/apps.py
payple_hj3415/models.py
payple_hj3415/services.py
payple_hj3415/urls.py
payple_hj3415/views.py
payple_hj3415/migrations/0001_initial.py
payple_hj3415/migrations/__init__.py
payple_hj3415/templates/payple_hj3415/payple_pay.html
payple_hj3415/templatetags/payple_tags.py
payple_hj3415-0.1.1.dist-info/WHEEL
payple_hj3415-0.1.1.dist-info/METADATA
payple_hj3415-0.1.1.dist-info/RECORD
