Metadata-Version: 2.4
Name: payple-hj3415
Version: 0.1.1
Summary: payple-hj3415 is the program for using payple
Author-email: Hyungjin Kim <hj3415@gmail.com>
Classifier: License :: OSI Approved :: MIT License
Requires-Dist: django
Requires-Dist: requests
Project-URL: Home, https://www.hyungjin.kr
